screenitshot/__init__.py
screenitshot/cli.py
screenitshot/templates/code.html
screenitshot/templates/csv.html
screenitshot/templates/docx.html
screenitshot/templates/epub.html
screenitshot/templates/geojson.html
screenitshot/templates/gpx.html
screenitshot/templates/html.html
screenitshot/templates/ipynb.html
screenitshot/templates/md.html
screenitshot/templates/mmd.html
screenitshot/templates/pdf.html
screenitshot/templates/pptx.html
screenitshot/templates/rtf.html
screenitshot/templates/tex.html
screenitshot/templates/url.html
screenitshot/templates/xlsx.html
screenitshot-0.7.1.dist-info/METADATA
screenitshot-0.7.1.dist-info/WHEEL
screenitshot-0.7.1.dist-info/entry_points.txt
screenitshot-0.7.1.dist-info/RECORD
