Metadata-Version: 2.4
Name: screenitshot
Version: 0.7.1
Summary: Convert various file formats to high-quality screenshots
Project-URL: Homepage, https://github.com/iloahz/screenitshot
Project-URL: Repository, https://github.com/iloahz/screenitshot
Author: screenitshot
License: MIT
Keywords: converter,docx,epub,pdf,pptx,screenshot,xlsx
Classifier: Development Status :: 3 - Alpha
Classifier: Intended Audience :: Developers
Classifier: License :: OSI Approved :: MIT License
Classifier: Programming Language :: Python :: 3
Classifier: Programming Language :: Python :: 3.8
Classifier: Programming Language :: Python :: 3.9
Classifier: Programming Language :: Python :: 3.10
Classifier: Programming Language :: Python :: 3.11
Classifier: Programming Language :: Python :: 3.12
Requires-Python: >=3.8
Requires-Dist: playwright>=1.40.0
